LICENSE
MANIFEST.in
README.rst
setup.py
plinth/__init__.py
plinth/channel.py
plinth/core.py
plinth/crypto.py
plinth/dht.py
plinth/exceptions.py
plinth/identity.py
plinth/line.py
plinth/log.py
plinth/packet.py
plinth/remote.py
plinth.egg-info/PKG-INFO
plinth.egg-info/SOURCES.txt
plinth.egg-info/dependency_links.txt
plinth.egg-info/requires.txt
plinth.egg-info/top_level.txt