Metadata-Version: 1.1
Name: plinth
Version: 0.0.14
Summary: Python Library for InterNetworking with TeleHash
Home-page: https://github.com/telehash/plinth
Author: David Van Duzer
Author-email: dvd@tennica.net
License: Copyright (c) 2013 David Van Duzer
